pipeline_utils/__init__.py
pipeline_utils/boundary_utils.py
pipeline_utils-0.0.2.dist-info/LICENSE
pipeline_utils-0.0.2.dist-info/METADATA
pipeline_utils-0.0.2.dist-info/WHEEL
pipeline_utils-0.0.2.dist-info/top_level.txt
pipeline_utils-0.0.2.dist-info/RECORD
