Metadata-Version: 2.1
Name: pipeline-utils
Version: 0.0.2
Summary: Utility functions for Coral Atlas Pipelines
Home-page: https://github.com/CoralMapping/proc_pipeline_utils
License: UNKNOWN
Platform: UNKNOWN
Classifier: Programming Language :: Python :: 3
Classifier: License :: OSI Approved :: Apache Software License
Classifier: Operating System :: OS Independent
Requires-Python: >=3.6
Requires-Dist: earthengine-api (>=0.1.239)
Requires-Dist: geeutils (>=0.3.0)
Requires-Dist: geojson (>=2.5.0)
